django_cowhite_cms/__init__.py
django_cowhite_cms/admin.py
django_cowhite_cms/apps.py
django_cowhite_cms/models.py
django_cowhite_cms/tests.py
django_cowhite_cms/urls.py
django_cowhite_cms/views.py
django_cowhite_cms/migrations/0001_initial.py
django_cowhite_cms/migrations/0002_auto_20180617_1802.py
django_cowhite_cms/migrations/0003_page_title_on_image.py
django_cowhite_cms/migrations/__init__.py
django_cowhite_cms/static/django_cowhite_cms/css/style.css
django_cowhite_cms/static/django_cowhite_cms/fonts/Roboto/LICENSE.txt
django_cowhite_cms/static/django_cowhite_cms/fonts/Roboto/Roboto-Black.ttf
django_cowhite_cms/static/django_cowhite_cms/fonts/Roboto/Roboto-BlackItalic.ttf
django_cowhite_cms/static/django_cowhite_cms/fonts/Roboto/Roboto-Bold.ttf
django_cowhite_cms/static/django_cowhite_cms/fonts/Roboto/Roboto-BoldItalic.ttf
django_cowhite_cms/static/django_cowhite_cms/fonts/Roboto/Roboto-Italic.ttf
django_cowhite_cms/static/django_cowhite_cms/fonts/Roboto/Roboto-Light.ttf
django_cowhite_cms/static/django_cowhite_cms/fonts/Roboto/Roboto-LightItalic.ttf
django_cowhite_cms/static/django_cowhite_cms/fonts/Roboto/Roboto-Medium.ttf
django_cowhite_cms/static/django_cowhite_cms/fonts/Roboto/Roboto-MediumItalic.ttf
django_cowhite_cms/static/django_cowhite_cms/fonts/Roboto/Roboto-Regular.ttf
django_cowhite_cms/static/django_cowhite_cms/fonts/Roboto/Roboto-Thin.ttf
django_cowhite_cms/static/django_cowhite_cms/fonts/Roboto/Roboto-ThinItalic.ttf
django_cowhite_cms/static/django_cowhite_cms/js/page_admin.js
django_cowhite_cms/static/django_cowhite_cms/lib/bootstrap-3.3.7-dist/css/bootstrap.min.css
django_cowhite_cms/static/django_cowhite_cms/lib/bootstrap-3.3.7-dist/css/bootstrap.min.css.map
django_cowhite_cms/static/django_cowhite_cms/lib/bootstrap-3.3.7-dist/fonts/glyphicons-halflings-regular.eot
django_cowhite_cms/static/django_cowhite_cms/lib/bootstrap-3.3.7-dist/fonts/glyphicons-halflings-regular.svg
django_cowhite_cms-0.3.3.dist-info/METADATA
django_cowhite_cms-0.3.3.dist-info/RECORD
django_cowhite_cms-0.3.3.dist-info/WHEEL
django_cowhite_cms-0.3.3.dist-info/top_level.txt
